{
  "categories": [
    {
      "name": "Cryptography/Encoder",
      "tools": [
        {
          "name": "Hash/Cryptography Online Tools",
          "url": "https://emn178.github.io/online-tools/"
        },
        {
          "name": "BASE64",
          "url": "https://www.base64decode.org/"
        },
        {
          "name": "RSA PKCS#1/PKCS#8 Converter",
          "url": "https://www.metools.info/code/c84.html"
        }
      ]
    },
    {
      "name": "Generator/Formatter",
      "tools": [
        {
          "name": "JSON Formatter",
          "url": "https://jsonformatter.org/"
        },
        {
          "name": "Password Generator",
          "url": "https://www.lastpass.com/features/password-generator"
        },
        {
          "name": "UUID Generator",
          "url": "https://www.uuidgenerator.net/"
        }
      ]
    },
    {
      "name": "Math/Algorithm",
      "tools": [
        {
          "name": "Function Curve",
          "url": "https://www.desmos.com/calculator"
        },
        {
          "name": "Graph Editor",
          "url": "https://csacademy.com/app/graph_editor/"
        }
      ]
    },
    {
      "name": "Other Tools",
      "tools": [
        {
          "name": "IP Location",
          "url": "https://ipwhois.io/"
        },
        {
          "name": "Timestamp Converter",
          "url": "https://www.epochconverter.com/"
        },
        {
          "name": "SSL Certificate Validation",
          "url": "https://www.ssllabs.com/ssltest/"
        },
        {
          "name": "Merge PDF",
          "url": "https://smallpdf.com/merge-pdf"
        },
        {
          "name": "Customize your CSS Border",
          "url": "https://kovart.github.io/dashed-border-generator/"
        }
      ]
    }
  ]
}
